<?xml version="1.0"?>
<EPP commandResponseTime="542.268" responsePath="API3_UK,API3_AU" tld="pl">
    <InfoDomainReply>
        <domainName>example.pl</domainName>
        <password/>
        <registrantId/>
        <roId>984490-NASK</roId>
        <sponsorClient>homepl</sponsorClient>
        <updateClient/>
        <createClient/>
        <createDate/>
        <expiryDate/>
        <transferDate/>
        <updateDate/>
        <nameServers/>
        <subordinateHosts/>
        <adminContacts/>
        <billingContacts/>
        <techContacts/>
        <rgpStatuses/>
        <rgpDates/>
        <idnScriptLanguage/>
        <statuses/>
    </InfoDomainReply>
    <trId>API3_AU-aa7456dc-d587-4be7-b876-c019aa0b4541</trId>
</EPP>